{
  "key": "plugin_content_manager_configuration_content_types::api::faq.faq",
  "value": {
    "settings": {
      "bulkable": true,
      "filterable": true,
      "searchable": true,
      "pageSize": 10,
      "mainField": "title",
      "defaultSortBy": "title",
      "defaultSortOrder": "ASC"
    },
    "metadatas": {
      "id": {
        "edit": {},
        "list": {
          "label": "id",
          "searchable": true,
          "sortable": true
        }
      },
      "title": {
        "edit": {
          "label": "Nadpis otázky",
          "description": "",
          "placeholder": "",
          "visible": true,
          "editable": true
        },
        "list": {
          "label": "title",
          "searchable": true,
          "sortable": true
        }
      },
      "faqCategory": {
        "edit": {
          "label": "Kategória",
          "description": "",
          "placeholder": "",
          "visible": true,
          "editable": true,
          "mainField": "title"
        },
        "list": {
          "label": "faqCategory",
          "searchable": true,
          "sortable": true
        }
      },
      "content": {
        "edit": {
          "label": "Text odpovede",
          "description": "",
          "placeholder": "",
          "visible": true,
          "editable": true
        },
        "list": {
          "label": "content",
          "searchable": false,
          "sortable": false
        }
      },
      "createdAt": {
        "edit": {
          "label": "createdAt",
          "description": "",
          "placeholder": "",
          "visible": false,
          "editable": true
        },
        "list": {
          "label": "createdAt",
          "searchable": true,
          "sortable": true
        }
      },
      "updatedAt": {
        "edit": {
          "label": "updatedAt",
          "description": "",
          "placeholder": "",
          "visible": false,
          "editable": true
        },
        "list": {
          "label": "updatedAt",
          "searchable": true,
          "sortable": true
        }
      },
      "createdBy": {
        "edit": {
          "label": "createdBy",
          "description": "",
          "placeholder": "",
          "visible": false,
          "editable": true,
          "mainField": "firstname"
        },
        "list": {
          "label": "createdBy",
          "searchable": true,
          "sortable": true
        }
      },
      "updatedBy": {
        "edit": {
          "label": "updatedBy",
          "description": "",
          "placeholder": "",
          "visible": false,
          "editable": true,
          "mainField": "firstname"
        },
        "list": {
          "label": "updatedBy",
          "searchable": true,
          "sortable": true
        }
      }
    },
    "layouts": {
      "edit": [
        [
          {
            "name": "faqCategory",
            "size": 6
          }
        ],
        [
          {
            "name": "title",
            "size": 12
          }
        ],
        [
          {
            "name": "content",
            "size": 12
          }
        ]
      ],
      "list": [
        "id",
        "title",
        "createdAt",
        "updatedAt"
      ]
    },
    "uid": "api::faq.faq"
  },
  "type": "object",
  "environment": null,
  "tag": null
}