{
  "collectionName": "components_header_sections_pickup_days",
  "info": {
    "displayName": "Odvozový deň",
    "description": ""
  },
  "options": {},
  "attributes": {
    "anchors": {
      "type": "component",
      "repeatable": true,
      "component": "items.anchor"
    },
    "carouselTitle": {
      "type": "string",
      "required": true
    },
    "tags": {
      "type": "relation",
      "relation": "oneToMany",
      "target": "api::tag.tag"
    },
    "showMoreLink": {
      "type": "component",
      "repeatable": false,
      "component": "items.link"
    }
  }
}
